palx/__init__.py
palx/main.py
palx-0.0.1.dist-info/LICENSE
palx-0.0.1.dist-info/METADATA
palx-0.0.1.dist-info/WHEEL
palx-0.0.1.dist-info/entry_points.txt
palx-0.0.1.dist-info/top_level.txt
palx-0.0.1.dist-info/RECORD
