Metadata-Version: 2.1
Name: palx
Version: 0.0.1
Summary: Palx - extract color palette from an image and reattach it to the image
Author-email: Anton Vice <antonvice@gmail.com>
Project-URL: Homepage, https://github.com/antonvice/palx
Project-URL: Issues, https://github.com/pypa/antonvice/palx
Classifier: Programming Language :: Python :: 3
Classifier: License :: OSI Approved :: MIT License
Classifier: Operating System :: MacOS
Requires-Python: >=3.9
License-File: LICENSE
Requires-Dist: Pillow
Requires-Dist: numpy
Requires-Dist: scikit-learn
